odoo/addons/account_invoice_customer_no_autofollow/README.rst
odoo/addons/account_invoice_customer_no_autofollow/__init__.py
odoo/addons/account_invoice_customer_no_autofollow/__manifest__.py
odoo/addons/account_invoice_customer_no_autofollow/i18n/account_invoice_customer_no_autofollow.pot
odoo/addons/account_invoice_customer_no_autofollow/models/__init__.py
odoo/addons/account_invoice_customer_no_autofollow/models/account_move.py
odoo/addons/account_invoice_customer_no_autofollow/models/res_config_settings.py
odoo/addons/account_invoice_customer_no_autofollow/readme/CONFIGURE.rst
odoo/addons/account_invoice_customer_no_autofollow/readme/CONTRIBUTORS.rst
odoo/addons/account_invoice_customer_no_autofollow/readme/DESCRIPTION.rst
odoo/addons/account_invoice_customer_no_autofollow/static/description/icon.png
odoo/addons/account_invoice_customer_no_autofollow/static/description/index.html
odoo/addons/account_invoice_customer_no_autofollow/tests/__init__.py
odoo/addons/account_invoice_customer_no_autofollow/tests/common.py
odoo/addons/account_invoice_customer_no_autofollow/tests/test_no_autofollow_disabled.py
odoo/addons/account_invoice_customer_no_autofollow/tests/test_no_autofollow_enabled.py
odoo/addons/account_invoice_customer_no_autofollow/views/res_config_settings.xml
odoo13_addon_account_invoice_customer_no_autofollow-13.0.1.0.1.dev2.dist-info/METADATA
odoo13_addon_account_invoice_customer_no_autofollow-13.0.1.0.1.dev2.dist-info/WHEEL
odoo13_addon_account_invoice_customer_no_autofollow-13.0.1.0.1.dev2.dist-info/top_level.txt
odoo13_addon_account_invoice_customer_no_autofollow-13.0.1.0.1.dev2.dist-info/RECORD
